BeginnersbookJavaJiaochengChuyiFix1/README.md
BeginnersbookJavaJiaochengChuyiFix1/__init__.py
BeginnersbookJavaJiaochengChuyiFix1/__main__.py
BeginnersbookJavaJiaochengChuyiFix1/file.epub
BeginnersbookJavaJiaochengChuyiFix1/index.html
BeginnersbookJavaJiaochengChuyiFix1/css/__init__.py
BeginnersbookJavaJiaochengChuyiFix1/css/annotations.css
BeginnersbookJavaJiaochengChuyiFix1/css/main.css
BeginnersbookJavaJiaochengChuyiFix1/css/normalize.css
BeginnersbookJavaJiaochengChuyiFix1/css/popup.css
BeginnersbookJavaJiaochengChuyiFix1/font/__init__.py
BeginnersbookJavaJiaochengChuyiFix1/font/fontello.eot
BeginnersbookJavaJiaochengChuyiFix1/font/fontello.svg
BeginnersbookJavaJiaochengChuyiFix1/font/fontello.ttf
BeginnersbookJavaJiaochengChuyiFix1/font/fontello.woff
BeginnersbookJavaJiaochengChuyiFix1/img/__init__.py
BeginnersbookJavaJiaochengChuyiFix1/img/annotator-glyph-sprite.png
BeginnersbookJavaJiaochengChuyiFix1/img/annotator-icon-sprite.png
BeginnersbookJavaJiaochengChuyiFix1/img/apple-touch-icon.png
BeginnersbookJavaJiaochengChuyiFix1/img/cancelfullscreen.png
BeginnersbookJavaJiaochengChuyiFix1/img/close.png
BeginnersbookJavaJiaochengChuyiFix1/img/fullscreen.png
BeginnersbookJavaJiaochengChuyiFix1/img/loader.gif
BeginnersbookJavaJiaochengChuyiFix1/img/menu-icon.png
BeginnersbookJavaJiaochengChuyiFix1/img/save.png
BeginnersbookJavaJiaochengChuyiFix1/img/saved.png
BeginnersbookJavaJiaochengChuyiFix1/img/settings-s.png
BeginnersbookJavaJiaochengChuyiFix1/img/settings.png
BeginnersbookJavaJiaochengChuyiFix1/img/star.png
BeginnersbookJavaJiaochengChuyiFix1/js/__init__.py
BeginnersbookJavaJiaochengChuyiFix1/js/epub.js
BeginnersbookJavaJiaochengChuyiFix1/js/epub.min.js
BeginnersbookJavaJiaochengChuyiFix1/js/epub.min.map
BeginnersbookJavaJiaochengChuyiFix1/js/hooks.min.js
BeginnersbookJavaJiaochengChuyiFix1/js/hooks.min.map
BeginnersbookJavaJiaochengChuyiFix1/js/reader.js
BeginnersbookJavaJiaochengChuyiFix1/js/reader.js.map
BeginnersbookJavaJiaochengChuyiFix1/js/reader.min.js
beginnersbook_java_jiaocheng_chuyi_fix1-2025.3.23.0.dist-info/METADATA
beginnersbook_java_jiaocheng_chuyi_fix1-2025.3.23.0.dist-info/WHEEL
beginnersbook_java_jiaocheng_chuyi_fix1-2025.3.23.0.dist-info/entry_points.txt
beginnersbook_java_jiaocheng_chuyi_fix1-2025.3.23.0.dist-info/top_level.txt
beginnersbook_java_jiaocheng_chuyi_fix1-2025.3.23.0.dist-info/RECORD
